vizra/__init__.py
vizra/agent.py
vizra/context.py
vizra/exceptions.py
vizra/py.typed
vizra/tool.py
vizra-0.1.0.dist-info/METADATA
vizra-0.1.0.dist-info/WHEEL
vizra-0.1.0.dist-info/top_level.txt
vizra-0.1.0.dist-info/RECORD
