Metadata-Version: 2.4
Name: vizra
Version: 0.1.0
Summary: A simple AI agent framework for Python
Home-page: https://github.com/yourusername/vizra
Author: Your Name
Author-email: Aaron Lumsden <aaronlumsden@me.com>
Maintainer-email: Aaron Lumsden <aaronlumsden@me.com>
License: MIT
Project-URL: Homepage, https://github.com/yourusername/vizra
Project-URL: Repository, https://github.com/yourusername/vizra.git
Project-URL: Issues, https://github.com/yourusername/vizra/issues
Project-URL: Documentation, https://vizra.readthedocs.io
Keywords: ai,agents,llm,openai,anthropic,litellm,framework
Classifier: Development Status :: 3 - Alpha
Classifier: Intended Audience :: Developers
Classifier: Topic :: Software Development :: Libraries :: Python Modules
Classifier: Topic :: Scientific/Engineering :: Artificial Intelligence
Classifier: License :: OSI Approved :: MIT License
Classifier: Programming Language :: Python :: 3
Classifier: Programming Language :: Python :: 3.8
Classifier: Programming Language :: Python :: 3.9
Classifier: Programming Language :: Python :: 3.10
Classifier: Programming Language :: Python :: 3.11
Classifier: Programming Language :: Python :: 3.12
Classifier: Operating System :: OS Independent
Classifier: Typing :: Typed
Requires-Python: >=3.8
Requires-Dist: litellm>=1.0.0
Requires-Dist: openai>=1.0.0
Provides-Extra: dev
Requires-Dist: pytest>=7.0.0; extra == "dev"
Requires-Dist: pytest-mock>=3.10.0; extra == "dev"
Requires-Dist: pytest-cov>=4.0.0; extra == "dev"
Requires-Dist: black>=23.0.0; extra == "dev"
Requires-Dist: ruff>=0.1.0; extra == "dev"
Requires-Dist: mypy>=1.0.0; extra == "dev"
Requires-Dist: pre-commit>=3.0.0; extra == "dev"
Provides-Extra: docs
Requires-Dist: mkdocs>=1.5.0; extra == "docs"
Requires-Dist: mkdocs-material>=9.0.0; extra == "docs"
Requires-Dist: mkdocstrings[python]>=0.24.0; extra == "docs"
Dynamic: author
Dynamic: home-page
Dynamic: requires-python
